python_log_indenter/pli.py
python_log_indenter/__init__.py
python_log_indenter/tests/test_indent_helper.py
python_log_indenter/tests/test_indent_logger.py
python_log_indenter/tests/test_named_queue.py
python_log_indenter/tests/__init__.py
python_log_indenter-0.9.dist-info/DESCRIPTION.rst
python_log_indenter-0.9.dist-info/METADATA
python_log_indenter-0.9.dist-info/metadata.json
python_log_indenter-0.9.dist-info/RECORD
python_log_indenter-0.9.dist-info/top_level.txt
python_log_indenter-0.9.dist-info/WHEEL
