Metadata-Version: 2.0
Name: python-log-indenter
Version: 0.9
Summary: A python LoggerAdapter class that provides automatic indenting for logging.
Home-page: http://python-log-indenter.readthedocs.org/en/latest/
Author: Dan Strohl
Author-email: dan@wjcg.net
License: GPLv2
Keywords: log LogAdapter indent logger logging extension plugin helper Logger readable
Platform: UNKNOWN
Classifier: Development Status :: 4 - Beta
Classifier: Intended Audience :: Developers
Classifier: License :: OSI Approved :: GNU General Public License v2 (GPLv2)
Classifier: Programming Language :: Python
Classifier: Programming Language :: Python :: 2.7
Classifier: Programming Language :: Python :: 3.2
Classifier: Programming Language :: Python :: 3.3
Classifier: Programming Language :: Python :: 3.4
Classifier: Topic :: Software Development :: Libraries :: Python Modules
Classifier: Topic :: Software Development :: Testing
Classifier: Topic :: System :: Logging
